aepp/__init__.py
aepp/__version__.py
aepp/accesscontrol.py
aepp/catalog.py
aepp/classmanager.py
aepp/config.py
aepp/configs.py
aepp/connector.py
aepp/customerprofile.py
aepp/dataaccess.py
aepp/dataprep.py
aepp/datasets.py
aepp/datatypemanager.py
aepp/deletion.py
aepp/destination.py
aepp/destinationinstanceservice.py
aepp/edge.py
aepp/exportDatasetToDataLandingZone.py
aepp/fieldgroupmanager.py
aepp/flowservice.py
aepp/hygiene.py
aepp/identity.py
aepp/ingestion.py
aepp/observability.py
aepp/policy.py
aepp/privacyservice.py
aepp/queryservice.py
aepp/sandboxes.py
aepp/schema.py
aepp/schemamanager.py
aepp/segmentation.py
aepp/sensei.py
aepp/som.py
aepp/synchronizer.py
aepp/tags.py
aepp/utils.py
aepp/cli/__init__.py
aepp/cli/__main__.py
aepp/cli/upsfieldsanalyzer.py
aepp-0.5.2.post2.dist-info/licenses/LICENSE
aepp-0.5.2.post2.dist-info/METADATA
aepp-0.5.2.post2.dist-info/WHEEL
aepp-0.5.2.post2.dist-info/entry_points.txt
aepp-0.5.2.post2.dist-info/top_level.txt
aepp-0.5.2.post2.dist-info/RECORD
