Metadata-Version: 2.4
Name: aepp
Version: 0.5.2.post2
Summary: Package to manage AEP API endpoint and some helper functions
Author-email: Julien Piccini <piccini.julien@gmail.com>
License: Apache-2.0
Project-URL: Homepage, https://github.com/adobe/aepp
Classifier: Programming Language :: Python :: 3
Classifier: Operating System :: OS Independent
Classifier: License :: OSI Approved :: Apache Software License
Classifier: Topic :: Utilities
Classifier: Topic :: Internet
Classifier: Topic :: Software Development :: Libraries
Classifier: Development Status :: 2 - Pre-Alpha
Requires-Python: >=3.10
License-File: LICENSE
Requires-Dist: pandas
Requires-Dist: requests
Requires-Dist: pathlib2
Requires-Dist: tenacity
Requires-Dist: deprecation
Requires-Dist: datamodel-code-generator
Requires-Dist: rich
Requires-Dist: matplotlib
Dynamic: license-file
